Workbook

Sheet Painel
A1: PAINEL DE CONTROLE — MUROS DO CONDOMÍNIO VILA FLORESTA
A2: Preencha as células amarelas. O restante da planilha calcula automaticamente os principais indicadores. | N2: Situação | O2: Valor
N3: Executado | O3: =G5
A4: Contratada | B4: Matias Magalhães Serviços de Engenharia Ltda. | G4: PROGRESSO FÍSICO | I4: ETAPAS CONCLUÍDAS | K4: ETAPAS EM ATRASO | N4: Restante | O4: =1-G5
A5: Data de início planejada | G5: =IFERROR(SUMPRODUCT(Cronograma!$I$7:$I$27,Cronograma!$J$7:$J$27)/SUM(Cronograma!$I$7:$I$27),0) | I5: =COUNTIF(Cronograma!$K$7:$K$27,"Concluída")&" de "&COUNTA(Cronograma!$A$7:$A$27) | K5: =SUMPRODUCT(--(Cronograma!$G$7:$G$27<>""),--(Cronograma!$G$7:$G$27<TODAY()),--(Cronograma!$K$7:$K$27<>"Concluída"))
A6: Prazo contratual | B6: 90 dias úteis
A7: Valor do contrato | B7: 125000 | G7: RECEBIDO | I7: DESPESAS PAGAS | K7: SALDO DE CAIXA
A8: Responsável técnico | B8: Thiago Lopes Magalhães dos Reis — CREA-RJ 2017119095 | G8: =SUMIF(Financeiro!$E$7:$E$10,"Pago",Financeiro!$G$7:$G$10) | I8: =SUMIF(Despesas!$H$7:$H$106,"Pago",Despesas!$G$7:$G$106) | K8: =G8-I8
A11: PROGRESSO POR MACROETAPA | G11: RESUMO FINANCEIRO
A12: Macroetapa | B12: Peso | C12: Executado | D12: % concluído | E12: Situação
A13: Mobilização e limpeza | B13: 0.06 | C13: =SUMIF(Cronograma!$B$7:$B$27,A13,Cronograma!$O$7:$O$27) | D13: =IFERROR(C13/B13,0) | E13: =IF(D13=1,"Concluída",IF(D13>0,"Em andamento","Não iniciada")) | G13: Valor contratado | J13: =B7
A14: Demolição | B14: 0.15 | C14: =SUMIF(Cronograma!$B$7:$B$27,A14,Cronograma!$O$7:$O$27) | D14: =IFERROR(C14/B14,0) | E14: =IF(D14=1,"Concluída",IF(D14>0,"Em andamento","Não iniciada")) | G14: Total recebido | J14: =G8
A15: Fundações | B15: 0.2 | C15: =SUMIF(Cronograma!$B$7:$B$27,A15,Cronograma!$O$7:$O$27) | D15: =IFERROR(C15/B15,0) | E15: =IF(D15=1,"Concluída",IF(D15>0,"Em andamento","Não iniciada")) | G15: Saldo a receber | J15: =B7-G8
A16: Estrutura | B16: 0.22 | C16: =SUMIF(Cronograma!$B$7:$B$27,A16,Cronograma!$O$7:$O$27) | D16: =IFERROR(C16/B16,0) | E16: =IF(D16=1,"Concluída",IF(D16>0,"Em andamento","Não iniciada")) | G16: Despesas registradas | J16: =SUM(Despesas!$G$7:$G$106)
A17: Alvenaria | B17: 0.25 | C17: =SUMIF(Cronograma!$B$7:$B$27,A17,Cronograma!$O$7:$O$27) | D17: =IFERROR(C17/B17,0) | E17: =IF(D17=1,"Concluída",IF(D17>0,"Em andamento","Não iniciada")) | G17: Despesas pagas | J17: =I8
A18: Concertina | B18: 0.05 | C18: =SUMIF(Cronograma!$B$7:$B$27,A18,Cronograma!$O$7:$O$27) | D18: =IFERROR(C18/B18,0) | E18: =IF(D18=1,"Concluída",IF(D18>0,"Em andamento","Não iniciada")) | G18: Resultado de caixa atual | J18: =G8-I8
A19: Entrega | B19: 0.07 | C19: =SUMIF(Cronograma!$B$7:$B$27,A19,Cronograma!$O$7:$O$27) | D19: =IFERROR(C19/B19,0) | E19: =IF(D19=1,"Concluída",IF(D19>0,"Em andamento","Não iniciada")) | G19: Margem empresarial planejada | J19: 11880

Sheet Cronograma
A1: CRONOGRAMA FÍSICO — CONTROLE DE ETAPAS
A2: Atualize a porcentagem e a situação. Ao concluir uma atividade, informe 100%, situação Concluída e a data real de término.
A4: Início planejado: | E4: =Painel!B5 | G4: Progresso físico total: | K4: =Painel!G5
A6: ID | B6: Macroetapa | C6: Atividade | D6: Trecho | E6: Predecessora | F6: Início planejado | G6: Fim planejado | H6: Dias úteis | I6: Peso físico | J6: % concluído | K6: Situação | L6: Início real | M6: Fim real | N6: Desvio (dias) | O6: Físico executado | P6: Observações | Q6: Conferência
A7: 1 | B7: Mobilização e limpeza | C7: Mobilização, canteiro, sinalização e segurança | D7: Geral | E7: - | F7: =IF(Painel!$B$5="","",WORKDAY.INTL(Painel!$B$5-1,1,1)) | G7: =IF(Painel!$B$5="","",WORKDAY.INTL(Painel!$B$5-1,5,1)) | H7: =IF(OR(F7="",G7=""),"",NETWORKDAYS.INTL(F7,G7,1)) | I7: 0.02 | J7: 0 | K7: Não iniciada | N7: =IF(M7<>"",NETWORKDAYS.INTL(G7,M7,1)-1,IF(AND(G7<>"",TODAY()>G7,K7<>"Concluída"),NETWORKDAYS.INTL(G7,TODAY(),1)-1,0)) | O7: =I7*J7 | Q7: =IF(AND(K7="Concluída",J7<1),"Atualizar %",IF(AND(J7=1,K7<>"Concluída"),"Marcar concluída",""))
A8: 2 | B8: Mobilização e limpeza | C8: Roçada e abertura dos acessos | D8: A | E8: 1 | F8: =IF(Painel!$B$5="","",WORKDAY.INTL(Painel!$B$5-1,1,1)) | G8: =IF(Painel!$B$5="","",WORKDAY.INTL(Painel!$B$5-1,10,1)) | H8: =IF(OR(F8="",G8=""),"",NETWORKDAYS.INTL(F8,G8,1)) | I8: 0.02 | J8: 0 | K8: Não iniciada | N8: =IF(M8<>"",NETWORKDAYS.INTL(G8,M8,1)-1,IF(AND(G8<>"",TODAY()>G8,K8<>"Concluída"),NETWORKDAYS.INTL(G8,TODAY(),1)-1,0)) | O8: =I8*J8 | Q8: =IF(AND(K8="Concluída",J8<1),"Atualizar %",IF(AND(J8=1,K8<>"Concluída"),"Marcar concluída",""))
A9: 3 | B9: Mobilização e limpeza | C9: Roçada e preparação do barranco | D9: B | E9: 1 | F9: =IF(Painel!$B$5="","",WORKDAY.INTL(Painel!$B$5-1,6,1)) | G9: =IF(Painel!$B$5="","",WORKDAY.INTL(Painel!$B$5-1,10,1)) | H9: =IF(OR(F9="",G9=""),"",NETWORKDAYS.INTL(F9,G9,1)) | I9: 0.01 | J9: 0 | K9: Não iniciada | N9: =IF(M9<>"",NETWORKDAYS.INTL(G9,M9,1)-1,IF(AND(G9<>"",TODAY()>G9,K9<>"Concluída"),NETWORKDAYS.INTL(G9,TODAY(),1)-1,0)) | O9: =I9*J9 | Q9: =IF(AND(K9="Concluída",J9<1),"Atualizar %",IF(AND(J9=1,K9<>"Concluída"),"Marcar concluída",""))
A10: 4 | B10: Mobilização e limpeza | C10: Limpeza e preparação da área | D10: C | E10: 1 | F10: =IF(Painel!$B$5="","",WORKDAY.INTL(Painel!$B$5-1,6,1)) | G10: =IF(Painel!$B$5="","",WORKDAY.INTL(Painel!$B$5-1,10,1)) | H10: =IF(OR(F10="",G10=""),"",NETWORKDAYS.INTL(F10,G10,1)) | I10: 0.01 | J10: 0 | K10: Não iniciada | N10: =IF(M10<>"",NETWORKDAYS.INTL(G10,M10,1)-1,IF(AND(G10<>"",TODAY()>G10,K10<>"Concluída"),NETWORKDAYS.INTL(G10,TODAY(),1)-1,0)) | O10: =I10*J10 | Q10: =IF(AND(K10="Concluída",J10<1),"Atualizar %",IF(AND(J10=1,K10<>"Concluída"),"Marcar concluída",""))
A11: 5 | B11: Demolição | C11: Demolição controlada e retirada de fundações | D11: A | E11: 2 | F11: =IF(Painel!$B$5="","",WORKDAY.INTL(Painel!$B$5-1,6,1)) | G11: =IF(Painel!$B$5="","",WORKDAY.INTL(Painel!$B$5-1,25,1)) | H11: =IF(OR(F11="",G11=""),"",NETWORKDAYS.INTL(F11,G11,1)) | I11: 0.1 | J11: 0 | K11: Não iniciada | N11: =IF(M11<>"",NETWORKDAYS.INTL(G11,M11,1)-1,IF(AND(G11<>"",TODAY()>G11,K11<>"Concluída"),NETWORKDAYS.INTL(G11,TODAY(),1)-1,0)) | O11: =I11*J11 | Q11: =IF(AND(K11="Concluída",J11<1),"Atualizar %",IF(AND(J11=1,K11<>"Concluída"),"Marcar concluída",""))
A12: 6 | B12: Demolição | C12: Demolição controlada e retirada de fundações | D12: B | E12: 3 | F12: =IF(Painel!$B$5="","",WORKDAY.INTL(Painel!$B$5-1,11,1)) | G12: =IF(Painel!$B$5="","",WORKDAY.INTL(Painel!$B$5-1,20,1)) | H12: =IF(OR(F12="",G12=""),"",NETWORKDAYS.INTL(F12,G12,1)) | I12: 0.03 | J12: 0 | K12: Não iniciada | N12: =IF(M12<>"",NETWORKDAYS.INTL(G12,M12,1)-1,IF(AND(G12<>"",TODAY()>G12,K12<>"Concluída"),NETWORKDAYS.INTL(G12,TODAY(),1)-1,0)) | O12: =I12*J12 | Q12: =IF(AND(K12="Concluída",J12<1),"Atualizar %",IF(AND(J12=1,K12<>"Concluída"),"Marcar concluída",""))
A13: 7 | B13: Demolição | C13: Demolição controlada e retirada de fundações | D13: C | E13: 4 | F13: =IF(Painel!$B$5="","",WORKDAY.INTL(Painel!$B$5-1,11,1)) | G13: =IF(Painel!$B$5="","",WORKDAY.INTL(Painel!$B$5-1,20,1)) | H13: =IF(OR(F13="",G13=""),"",NETWORKDAYS.INTL(F13,G13,1)) | I13: 0.02 | J13: 0 | K13: Não iniciada | N13: =IF(M13<>"",NETWORKDAYS.INTL(G13,M13,1)-1,IF(AND(G13<>"",TODAY()>G13,K13<>"Concluída"),NETWORKDAYS.INTL(G13,TODAY(),1)-1,0)) | O13: =I13*J13 | Q13: =IF(AND(K13="Concluída",J13<1),"Atualizar %",IF(AND(J13=1,K13<>"Concluída"),"Marcar concluída",""))
A14: 8 | B14: Fundações | C14: Locação, escavação, sapatas e baldrame | D14: A | E14: 5 | F14: =IF(Painel!$B$5="","",WORKDAY.INTL(Painel!$B$5-1,21,1)) | G14: =IF(Painel!$B$5="","",WORKDAY.INTL(Painel!$B$5-1,40,1)) | H14: =IF(OR(F14="",G14=""),"",NETWORKDAYS.INTL(F14,G14,1)) | I14: 0.14 | J14: 0 | K14: Não iniciada | N14: =IF(M14<>"",NETWORKDAYS.INTL(G14,M14,1)-1,IF(AND(G14<>"",TODAY()>G14,K14<>"Concluída"),NETWORKDAYS.INTL(G14,TODAY(),1)-1,0)) | O14: =I14*J14 | Q14: =IF(AND(K14="Concluída",J14<1),"Atualizar %",IF(AND(J14=1,K14<>"Concluída"),"Marcar concluída",""))
A15: 9 | B15: Fundações | C15: Locação, escavação, sapatas e baldrame | D15: B | E15: 6 | F15: =IF(Painel!$B$5="","",WORKDAY.INTL(Painel!$B$5-1,26,1)) | G15: =IF(Painel!$B$5="","",WORKDAY.INTL(Painel!$B$5-1,40,1)) | H15: =IF(OR(F15="",G15=""),"",NETWORKDAYS.INTL(F15,G15,1)) | I15: 0.03 | J15: 0 | K15: Não iniciada | N15: =IF(M15<>"",NETWORKDAYS.INTL(G15,M15,1)-1,IF(AND(G15<>"",TODAY()>G15,K15<>"Concluída"),NETWORKDAYS.INTL(G15,TODAY(),1)-1,0)) | O15: =I15*J15 | Q15: =IF(AND(K15="Concluída",J15<1),"Atualizar %",IF(AND(J15=1,K15<>"Concluída"),"Marcar concluída",""))
A16: 10 | B16: Fundações | C16: Locação, escavação, sapatas e baldrame | D16: C | E16: 7 | F16: =IF(Painel!$B$5="","",WORKDAY.INTL(Painel!$B$5-1,16,1)) | G16: =IF(Painel!$B$5="","",WORKDAY.INTL(Painel!$B$5-1,30,1)) | H16: =IF(OR(F16="",G16=""),"",NETWORKDAYS.INTL(F16,G16,1)) | I16: 0.03 | J16: 0 | K16: Não iniciada | N16: =IF(M16<>"",NETWORKDAYS.INTL(G16,M16,1)-1,IF(AND(G16<>"",TODAY()>G16,K16<>"Concluída"),NETWORKDAYS.INTL(G16,TODAY(),1)-1,0)) | O16: =I16*J16 | Q16: =IF(AND(K16="Concluída",J16<1),"Atualizar %",IF(AND(J16=1,K16<>"Concluída"),"Marcar concluída",""))
A17: 11 | B17: Estrutura | C17: Pilares e vigas de concreto armado | D17: A | E17: 8 | F17: =IF(Painel!$B$5="","",WORKDAY.INTL(Painel!$B$5-1,31,1)) | G17: =IF(Painel!$B$5="","",WORKDAY.INTL(Painel!$B$5-1,60,1)) | H17: =IF(OR(F17="",G17=""),"",NETWORKDAYS.INTL(F17,G17,1)) | I17: 0.15 | J17: 0 | K17: Não iniciada | N17: =IF(M17<>"",NETWORKDAYS.INTL(G17,M17,1)-1,IF(AND(G17<>"",TODAY()>G17,K17<>"Concluída"),NETWORKDAYS.INTL(G17,TODAY(),1)-1,0)) | O17: =I17*J17 | Q17: =IF(AND(K17="Concluída",J17<1),"Atualizar %",IF(AND(J17=1,K17<>"Concluída"),"Marcar concluída",""))
A18: 12 | B18: Estrutura | C18: Pilares e vigas de concreto armado | D18: B | E18: 9 | F18: =IF(Painel!$B$5="","",WORKDAY.INTL(Painel!$B$5-1,36,1)) | G18: =IF(Painel!$B$5="","",WORKDAY.INTL(Painel!$B$5-1,60,1)) | H18: =IF(OR(F18="",G18=""),"",NETWORKDAYS.INTL(F18,G18,1)) | I18: 0.04 | J18: 0 | K18: Não iniciada | N18: =IF(M18<>"",NETWORKDAYS.INTL(G18,M18,1)-1,IF(AND(G18<>"",TODAY()>G18,K18<>"Concluída"),NETWORKDAYS.INTL(G18,TODAY(),1)-1,0)) | O18: =I18*J18 | Q18: =IF(AND(K18="Concluída",J18<1),"Atualizar %",IF(AND(J18=1,K18<>"Concluída"),"Marcar concluída",""))
A19: 13 | B19: Estrutura | C19: Pilares e vigas de concreto armado | D19: C | E19: 10 | F19: =IF(Painel!$B$5="","",WORKDAY.INTL(Painel!$B$5-1,26,1)) | G19: =IF(Painel!$B$5="","",WORKDAY.INTL(Painel!$B$5-1,50,1)) | H19: =IF(OR(F19="",G19=""),"",NETWORKDAYS.INTL(F19,G19,1)) | I19: 0.03 | J19: 0 | K19: Não iniciada | N19: =IF(M19<>"",NETWORKDAYS.INTL(G19,M19,1)-1,IF(AND(G19<>"",TODAY()>G19,K19<>"Concluída"),NETWORKDAYS.INTL(G19,TODAY(),1)-1,0)) | O19: =I19*J19 | Q19: =IF(AND(K19="Concluída",J19<1),"Atualizar %",IF(AND(J19=1,K19<>"Concluída"),"Marcar concluída",""))
A20: 14 | B20: Alvenaria | C20: Alvenaria estrutural aparente | D20: A | E20: 11 | F20: =IF(Painel!$B$5="","",WORKDAY.INTL(Painel!$B$5-1,46,1)) | G20: =IF(Painel!$B$5="","",WORKDAY.INTL(Painel!$B$5-1,80,1)) | H20: =IF(OR(F20="",G20=""),"",NETWORKDAYS.INTL(F20,G20,1)) | I20: 0.17 | J20: 0 | K20: Não iniciada | N20: =IF(M20<>"",NETWORKDAYS.INTL(G20,M20,1)-1,IF(AND(G20<>"",TODAY()>G20,K20<>"Concluída"),NETWORKDAYS.INTL(G20,TODAY(),1)-1,0)) | O20: =I20*J20 | Q20: =IF(AND(K20="Concluída",J20<1),"Atualizar %",IF(AND(J20=1,K20<>"Concluída"),"Marcar concluída",""))
A21: 15 | B21: Alvenaria | C21: Alvenaria estrutural aparente | D21: B | E21: 12 | F21: =IF(Painel!$B$5="","",WORKDAY.INTL(Painel!$B$5-1,51,1)) | G21: =IF(Painel!$B$5="","",WORKDAY.INTL(Painel!$B$5-1,75,1)) | H21: =IF(OR(F21="",G21=""),"",NETWORKDAYS.INTL(F21,G21,1)) | I21: 0.04 | J21: 0 | K21: Não iniciada | N21: =IF(M21<>"",NETWORKDAYS.INTL(G21,M21,1)-1,IF(AND(G21<>"",TODAY()>G21,K21<>"Concluída"),NETWORKDAYS.INTL(G21,TODAY(),1)-1,0)) | O21: =I21*J21 | Q21: =IF(AND(K21="Concluída",J21<1),"Atualizar %",IF(AND(J21=1,K21<>"Concluída"),"Marcar concluída",""))
A22: 16 | B22: Alvenaria | C22: Alvenaria estrutural aparente | D22: C | E22: 13 | F22: =IF(Painel!$B$5="","",WORKDAY.INTL(Painel!$B$5-1,41,1)) | G22: =IF(Painel!$B$5="","",WORKDAY.INTL(Painel!$B$5-1,65,1)) | H22: =IF(OR(F22="",G22=""),"",NETWORKDAYS.INTL(F22,G22,1)) | I22: 0.04 | J22: 0 | K22: Não iniciada | N22: =IF(M22<>"",NETWORKDAYS.INTL(G22,M22,1)-1,IF(AND(G22<>"",TODAY()>G22,K22<>"Concluída"),NETWORKDAYS.INTL(G22,TODAY(),1)-1,0)) | O22: =I22*J22 | Q22: =IF(AND(K22="Concluída",J22<1),"Atualizar %",IF(AND(J22=1,K22<>"Concluída"),"Marcar concluída",""))
A23: 17 | B23: Concertina | C23: Instalação da concertina | D23: A | E23: 14 | F23: =IF(Painel!$B$5="","",WORKDAY.INTL(Painel!$B$5-1,76,1)) | G23: =IF(Painel!$B$5="","",WORKDAY.INTL(Painel!$B$5-1,85,1)) | H23: =IF(OR(F23="",G23=""),"",NETWORKDAYS.INTL(F23,G23,1)) | I23: 0.03 | J23: 0 | K23: Não iniciada | N23: =IF(M23<>"",NETWORKDAYS.INTL(G23,M23,1)-1,IF(AND(G23<>"",TODAY()>G23,K23<>"Concluída"),NETWORKDAYS.INTL(G23,TODAY(),1)-1,0)) | O23: =I23*J23 | Q23: =IF(AND(K23="Concluída",J23<1),"Atualizar %",IF(AND(J23=1,K23<>"Concluída"),"Marcar concluída",""))
A24: 18 | B24: Concertina | C24: Instalação da concertina | D24: B | E24: 15 | F24: =IF(Painel!$B$5="","",WORKDAY.INTL(Painel!$B$5-1,81,1)) | G24: =IF(Painel!$B$5="","",WORKDAY.INTL(Painel!$B$5-1,85,1)) | H24: =IF(OR(F24="",G24=""),"",NETWORKDAYS.INTL(F24,G24,1)) | I24: 0.01 | J24: 0 | K24: Não iniciada | N24: =IF(M24<>"",NETWORKDAYS.INTL(G24,M24,1)-1,IF(AND(G24<>"",TODAY()>G24,K24<>"Concluída"),NETWORKDAYS.INTL(G24,TODAY(),1)-1,0)) | O24: =I24*J24 | Q24: =IF(AND(K24="Concluída",J24<1),"Atualizar %",IF(AND(J24=1,K24<>"Concluída"),"Marcar concluída",""))
A25: 19 | B25: Concertina | C25: Instalação da concertina | D25: C | E25: 16 | F25: =IF(Painel!$B$5="","",WORKDAY.INTL(Painel!$B$5-1,76,1)) | G25: =IF(Painel!$B$5="","",WORKDAY.INTL(Painel!$B$5-1,85,1)) | H25: =IF(OR(F25="",G25=""),"",NETWORKDAYS.INTL(F25,G25,1)) | I25: 0.01 | J25: 0 | K25: Não iniciada | N25: =IF(M25<>"",NETWORKDAYS.INTL(G25,M25,1)-1,IF(AND(G25<>"",TODAY()>G25,K25<>"Concluída"),NETWORKDAYS.INTL(G25,TODAY(),1)-1,0)) | O25: =I25*J25 | Q25: =IF(AND(K25="Concluída",J25<1),"Atualizar %",IF(AND(J25=1,K25<>"Concluída"),"Marcar concluída",""))
A26: 20 | B26: Entrega | C26: Arremates e limpeza final | D26: Geral | E26: 17, 18, 19 | F26: =IF(Painel!$B$5="","",WORKDAY.INTL(Painel!$B$5-1,81,1)) | G26: =IF(Painel!$B$5="","",WORKDAY.INTL(Painel!$B$5-1,88,1)) | H26: =IF(OR(F26="",G26=""),"",NETWORKDAYS.INTL(F26,G26,1)) | I26: 0.04 | J26: 0 | K26: Não iniciada | N26: =IF(M26<>"",NETWORKDAYS.INTL(G26,M26,1)-1,IF(AND(G26<>"",TODAY()>G26,K26<>"Concluída"),NETWORKDAYS.INTL(G26,TODAY(),1)-1,0)) | O26: =I26*J26 | Q26: =IF(AND(K26="Concluída",J26<1),"Atualizar %",IF(AND(J26=1,K26<>"Concluída"),"Marcar concluída",""))
A27: 21 | B27: Entrega | C27: Inspeção, correções e entrega técnica | D27: Geral | E27: 20 | F27: =IF(Painel!$B$5="","",WORKDAY.INTL(Painel!$B$5-1,89,1)) | G27: =IF(Painel!$B$5="","",WORKDAY.INTL(Painel!$B$5-1,90,1)) | H27: =IF(OR(F27="",G27=""),"",NETWORKDAYS.INTL(F27,G27,1)) | I27: 0.03 | J27: 0 | K27: Não iniciada | N27: =IF(M27<>"",NETWORKDAYS.INTL(G27,M27,1)-1,IF(AND(G27<>"",TODAY()>G27,K27<>"Concluída"),NETWORKDAYS.INTL(G27,TODAY(),1)-1,0)) | O27: =I27*J27 | Q27: =IF(AND(K27="Concluída",J27<1),"Atualizar %",IF(AND(J27=1,K27<>"Concluída"),"Marcar concluída",""))

Sheet Financeiro
A1: CRONOGRAMA FINANCEIRO — RECEBIMENTOS
A2: Atualize situação, data e valor efetivamente recebido. As datas previstas são calculadas a partir da data inicial do Painel.
A4: Valor do contrato | C4: =Painel!B7 | E4: Total recebido | G4: =SUMIF(E7:E10,"Pago",G7:G10) | I4: Saldo a receber | K4: =C4-G4
A6: Parcela | B6: Evento | C6: Vencimento previsto | D6: Valor previsto | E6: Situação | F6: Data recebida | G6: Valor recebido | H6: Documento/NF | I6: Dias de atraso | J6: Observações
A7: Entrada | B7: Assinatura / mobilização | C7: =IF(Painel!$B$5="","",Painel!$B$5) | D7: 50000 | E7: Pendente | G7: 0 | I7: =IF(OR(C7="",E7="Pago"),0,MAX(0,TODAY()-C7))
A8: 1ª parcela | B8: 30 dias após o início | C8: =IF(Painel!$B$5="","",EDATE(Painel!$B$5,1)) | D8: 25000 | E8: Pendente | G8: 0 | I8: =IF(OR(C8="",E8="Pago"),0,MAX(0,TODAY()-C8))
A9: 2ª parcela | B9: 60 dias após o início | C9: =IF(Painel!$B$5="","",EDATE(Painel!$B$5,2)) | D9: 25000 | E9: Pendente | G9: 0 | I9: =IF(OR(C9="",E9="Pago"),0,MAX(0,TODAY()-C9))
A10: 3ª parcela | B10: 90 dias após o início | C10: =IF(Painel!$B$5="","",EDATE(Painel!$B$5,3)) | D10: 25000 | E10: Pendente | G10: 0 | I10: =IF(OR(C10="",E10="Pago"),0,MAX(0,TODAY()-C10))

Sheet Despesas
A1: CONTROLE DE DESPESAS E CUSTOS
A2: Registre cada gasto individualmente. Não use a margem planejada como despesa. Anexe ou identifique o comprovante sempre que possível.
A4: Orçamento de custos e reservas | C4: 113120 | E4: Despesas registradas | G4: =SUM(G7:G106) | I4: Saldo do orçamento | K4: =C4-G4
A6: Data | B6: Categoria | C6: Fornecedor/MEI | D6: Descrição | E6: Documento/NF | F6: Valor previsto | G6: Valor realizado | H6: Situação | I6: Data pagamento | J6: Forma de pagamento | K6: Trecho | L6: Observações
H7: Pendente | K7: Geral
H8: Pendente | K8: Geral
H9: Pendente | K9: Geral
H10: Pendente | K10: Geral
H11: Pendente | K11: Geral
H12: Pendente | K12: Geral
H13: Pendente | K13: Geral
H14: Pendente | K14: Geral
H15: Pendente | K15: Geral
H16: Pendente | K16: Geral
H17: Pendente | K17: Geral
H18: Pendente | K18: Geral
... H106: Pendente | K106: Geral

Sheet Materiais
A1: CONTROLE DE MATERIAIS — FORNECIMENTO DO CONDOMÍNIO
A2: Preencha solicitado, entregue e utilizado. O saldo e o alerta de reposição são calculados automaticamente. Quantidades permanecem preliminares até a conferência executiva.
A6: Item | B6: Unidade | C6: Qtd. preliminar | D6: Qtd. solicitada | E6: Qtd. entregue | F6: Qtd. utilizada | G6: Saldo disponível | H6: A entregar | I6: Data necessária | J6: Entrega prevista | K6: Entrega realizada | L6: Fornecedor | M6: Situação | N6: Observações
A7: Bloco estrutural 9 × 19 × 39 cm | B7: un | C7: 3635 | G7: =E7-F7 | H7: =MAX(0,D7-E7) | M7: Não solicitado
A8: Concreto estrutural fck 25 MPa | B8: m³ | C8: 21.5 | G8: =E8-F8 | H8: =MAX(0,D8-E8) | M8: Não solicitado
A9: Aço CA-50/CA-60 | B9: kg | C9: 2000 | G9: =E9-F9 | H9: =MAX(0,D9-E9) | M9: Não solicitado
A10: Argamassa de assentamento | B10: m³ | C10: 4 | G10: =E10-F10 | H10: =MAX(0,D10-E10) | M10: Não solicitado
A11: Cimento | B11: saco | G11: =E11-F11 | H11: =MAX(0,D11-E11) | M11: Não solicitado
A12: Areia | B12: m³ | G12: =E12-F12 | H12: =MAX(0,D12-E12) | M12: Não solicitado
A13: Brita | B13: m³ | G13: =E13-F13 | H13: =MAX(0,D13-E13) | M13: Não solicitado
A14: Concertina simples Ø 50 cm | B14: m | C14: 97 | G14: =E14-F14 | H14: =MAX(0,D14-E14) | M14: Não solicitado
A15: Suportes e fixadores de concertina | B15: conjunto | G15: =E15-F15 | H15: =MAX(0,D15-E15) | M15: Não solicitado
A16: Caçamba de 5 m³ | B16: un | C16: 12 | G16: =E16-F16 | H16: =MAX(0,D16-E16) | M16: Não solicitado

Sheet Medições
A1: MEDIÇÕES E MARCOS DA OBRA
A2: Registre a medição mensal, anexe evidências e compare o avanço planejado com o realizado antes de emitir o relatório ao condomínio.
A6: Medição | B6: Período | C6: Data da vistoria | D6: Físico planejado acum. | E6: Físico realizado acum. | F6: Desvio físico | G6: Valor contratual | H6: Valor recebido acum. | I6: Relatório emitido? | J6: Aprovado por | K6: Situação | L6: Observações
A7: Medição 1 | B7: Mês 1 | D7: 0.25 | E7: 0 | F7: =E7-D7 | G7: 125000 | H7: 75000 | I7: Não | K7: Pendente
A8: Medição 2 | B8: Mês 2 | D8: 0.5 | E8: 0 | F8: =E8-D8 | G8: 125000 | H8: 100000 | I8: Não | K8: Pendente
A9: Medição 3 | B9: Mês 3 | D9: 0.75 | E9: 0 | F9: =E9-D9 | G9: 125000 | H9: 125000 | I9: Não | K9: Pendente
A10: Medição final | B10: Mês 4 | D10: 1 | E10: 0 | F10: =E10-D10 | G10: 125000 | H10: 125000 | I10: Não | K10: Pendente

Sheet Diário de Obra
A1: DIÁRIO DE OBRA
A2: Faça um registro por dia trabalhado, incluindo ocorrências, efetivo, segurança, materiais e evidências fotográficas.
A6: Data | B6: Dia | C6: Clima | D6: Trecho | E6: Pedreiros | F6: Serventes | G6: Horas trabalhadas | H6: Atividades executadas | I6: Materiais recebidos/usados | J6: Equipamentos | K6: Segurança/DDS | L6: Ocorrências e paralisações | M6: Fotos/links | N6: Responsável
B7: =IF(A7="","",TEXT(A7,"dddd")) | D7: Geral | E7: 1 | F7: 4
B8: =IF(A8="","",TEXT(A8,"dddd")) | D8: Geral | E8: 1 | F8: 4
B9: =IF(A9="","",TEXT(A9,"dddd")) | D9: Geral | E9: 1 | F9: 4
B10: =IF(A10="","",TEXT(A10,"dddd")) | D10: Geral | E10: 1 | F10: 4
B11: =IF(A11="","",TEXT(A11,"dddd")) | D11: Geral | E11: 1 | F11: 4
B12: =IF(A12="","",TEXT(A12,"dddd")) | D12: Geral | E12: 1 | F12: 4
B13: =IF(A13="","",TEXT(A13,"dddd")) | D13: Geral | E13: 1 | F13: 4
B14: =IF(A14="","",TEXT(A14,"dddd")) | D14: Geral | E14: 1 | F14: 4
B15: =IF(A15="","",TEXT(A15,"dddd")) | D15: Geral | E15: 1 | F15: 4
B16: =IF(A16="","",TEXT(A16,"dddd")) | D16: Geral | E16: 1 | F16: 4
B17: =IF(A17="","",TEXT(A17,"dddd")) | D17: Geral | E17: 1 | F17: 4
B18: =IF(A18="","",TEXT(A18,"dddd")) | D18: Geral | E18: 1 | F18: 4
... B106: =IF(A106="","",TEXT(A106,"dddd")) | D106: Geral | E106: 1 | F106: 4

Sheet Instruções
A1: COMO USAR ESTA PLANILHA
A3: 1. Defina a data de início
A4: No Painel, preencha a célula amarela “Data de início planejada”. O cronograma e as datas das parcelas serão calculados automaticamente.
A6: 2. Atualize o cronograma
A7: Na aba Cronograma, informe o percentual concluído, a situação e as datas reais. Use 100% e “Concluída” quando a etapa terminar.
A9: 3. Registre recebimentos
A10: Na aba Financeiro, atualize a situação, data e valor recebido de cada parcela.
A12: 4. Registre todas as despesas
A13: Use uma linha por gasto na aba Despesas. Informe nota fiscal ou comprovante e marque como pago somente após a quitação.
A15: 5. Controle os materiais
A16: Na aba Materiais, acompanhe o que foi solicitado, entregue e consumido. A coluna “A entregar” mostra possíveis faltas.
A18: 6. Faça medições mensais
... A25: Salve uma cópia semanal com a data no nome do arquivo e mantenha comprovantes e fotos em pasta vinculada à obra.
